{
  "Neeko": {
    "mid": {
      "Vel'Koz": {
        "difficulty": "hard",
        "who_wins_early": "Vel'Koz",
        "trading_pattern": "Vel'Koz outranges significantly. Farm safely with E.",
        "ability_to_dodge": "Vel'Koz E — dodge away.",
        "power_spikes": {
          "you": "Level 6 (ult), Luden's",
          "enemy": "Luden's, Level 6"
        },
        "early_game": "Farm defensively. His range dominates.",
        "mid_game": "Use ult for teamfight engagement. Scale with team.",
        "late_game": "He outscales in poke. Use ult for teamfights.",
        "win_condition": "Use ult to engage teamfights.",
        "counter_items": ["Mercury's Treads", "Banshee's Veil"],
        "scaling": "Vel'Koz outscales — his poke is oppressive late",
        "jungle_gankable": false,
        "positioning": "Keep distance. Farm safely."
      },
      "Veigar": {
        "difficulty": "hard",
        "who_wins_early": "Veigar",
        "trading_pattern": "Veigar stacks early. Trade before stacks accumulate.",
        "ability_to_dodge": "Veigar E (Event Horizon) — dodge immediately.",
        "power_spikes": {
          "you": "Level 6 (ult), Luden's",
          "enemy": "Stacks, Level 6"
        },
        "early_game": "Abuse before stacks. Poke with Q.",
        "mid_game": "Use ult to engage. Avoid his cage.",
        "late_game": "He outscales. Use ult for teamfights.",
        "win_condition": "Abuse early before stacks. Use ult for teamfights.",
        "counter_items": ["Mercury's Treads", "Banshee's Veil"],
        "scaling": "Veigar significantly outscales — stacking makes him oppressive",
        "jungle_gankable": true,
        "positioning": "Avoid his cage. Use ult for engagement."
      },
      "Annie": {
        "difficulty": "medium",
        "who_wins_early": "Annie",
        "trading_pattern": "Annie has burst. Trade when stun down.",
        "ability_to_dodge": "Annie Q — dodge by moving away.",
        "power_spikes": {
          "you": "Level 6 (ult), Luden's",
          "enemy": "Level 6 (Tibbers), Luden's"
        },
        "early_game": "Play defensively. Annie has burst.",
        "mid_game": "Use ult to engage teamfights. Scale with team.",
        "late_game": "Both scale similarly. Teamfights determine outcome.",
        "win_condition": "Use ult to engage and chain teamfights.",
        "counter_items": ["Mercury's Treads", "Banshee's Veil"],
        "scaling": "Neeko slightly favored — your ult utility is superior",
        "jungle_gankable": true,
        "positioning": "Keep distance. Use ult for teamfights."
      },
      "Ekko": {
        "difficulty": "medium",
        "who_wins_early": "Ekko",
        "trading_pattern": "Ekko is mobile. Trade when abilities down.",
        "ability_to_dodge": "Ekko W (Zone) — avoid zone.",
        "power_spikes": {
          "you": "Level 6 (ult), Luden's",
          "enemy": "Protobelt, Level 6"
        },
        "early_game": "Play defensively. Ekko has poke.",
        "mid_game": "Use ult to engage teamfights. Both scale.",
        "late_game": "Both scale similarly. Teamfights determine outcome.",
        "win_condition": "Use ult to engage and chain teamfights.",
        "counter_items": ["Mercury's Treads", "Banshee's Veil"],
        "scaling": "Even — both scale at similar rates",
        "jungle_gankable": true,
        "positioning": "Keep distance. Use ult for teamfights."
      },
      "Twisted Fate": {
        "difficulty": "medium",
        "who_wins_early": "Twisted Fate",
        "trading_pattern": "Twisted Fate has poke and CC. Trade carefully.",
        "ability_to_dodge": "Twisted Fate W (Pick a Card) — respect gold card.",
        "power_spikes": {
          "you": "Level 6 (ult), Luden's",
          "enemy": "Level 6 (roams), Luden's"
        },
        "early_game": "Play defensively. TF has poke.",
        "mid_game": "Both roam. Use ult to engage teamfights.",
        "late_game": "Both scale similarly. Teamfights determine outcome.",
        "win_condition": "Use ult to engage and chain teamfights.",
        "counter_items": ["Mercury's Treads", "Banshee's Veil"],
        "scaling": "Even — both scale at similar rates",
        "jungle_gankable": true,
        "positioning": "Keep distance. Use ult for engagement."
      },
      "Aurelion Sol": {
        "difficulty": "hard",
        "who_wins_early": "Aurelion Sol",
        "trading_pattern": "Aurelion Sol pushes and roams better. Farm defensively.",
        "ability_to_dodge": "Aurelion Sol W — stay at range.",
        "power_spikes": {
          "you": "Level 6 (ult), Luden's",
          "enemy": "Level 6 (roams), Luden's"
        },
        "early_game": "Farm defensively. He roams better early.",
        "mid_game": "Use ult to engage teamfights. Avoid getting caught.",
        "late_game": "He outscales in roaming. Use ult for teamfights.",
        "win_condition": "Use ult to engage and win teamfights.",
        "counter_items": ["Mercury's Treads", "Banshee's Veil"],
        "scaling": "Aurelion Sol outscales — his roaming dominates late",
        "jungle_gankable": true,
        "positioning": "Keep distance. Use ult for teamfights."
      },
      "Smolder": {
        "difficulty": "easy",
        "who_wins_early": "Neeko",
        "trading_pattern": "Smolder weak early. Spam E poke and farm.",
        "ability_to_dodge": "Smolder Q — dodge away.",
        "power_spikes": {
          "you": "Level 6 (ult), Luden's",
          "enemy": "Liandry's, Level 13"
        },
        "early_game": "Dominate with E poke. Control lane.",
        "mid_game": "Maintain pressure. Don't let him scale.",
        "late_game": "He outscales. Finish before 2-3 items.",
        "win_condition": "Get early lead. Finish before he scales.",
        "counter_items": ["Mercury's Treads", "Banshee's Veil"],
        "scaling": "Smolder significantly outscales — you need major lead",
        "jungle_gankable": false,
        "positioning": "Spam E aggressively. Control lane."
      },
      "Taliyah": {
        "difficulty": "medium",
        "who_wins_early": "Taliyah",
        "trading_pattern": "Taliyah has waveclear. Farm when abilities down.",
        "ability_to_dodge": "Taliyah Q — dodge perpendicular.",
        "power_spikes": {
          "you": "Level 6 (ult), Luden's",
          "enemy": "Luden's, Level 6"
        },
        "early_game": "Play defensively. Taliyah pushes better.",
        "mid_game": "Use ult to engage teamfights. Both roam.",
        "late_game": "Both scale similarly. Teamfights determine outcome.",
        "win_condition": "Use ult to engage and win teamfights.",
        "counter_items": ["Mercury's Treads", "Banshee's Veil"],
        "scaling": "Taliyah slightly favored — her roaming is stronger",
        "jungle_gankable": true,
        "positioning": "Keep distance. Use ult for teamfights."
      },
      "Ahri": {
        "difficulty": "medium",
        "who_wins_early": "Ahri",
        "trading_pattern": "Ahri has poke and mobility. Trade when Q down.",
        "ability_to_dodge": "Ahri Q — dodge sideways.",
        "power_spikes": {
          "you": "Level 6 (ult), Luden's",
          "enemy": "Luden's, Level 6"
        },
        "early_game": "Play defensively. Ahri has poke.",
        "mid_game": "Use ult to engage teamfights. Both roam.",
        "late_game": "Both scale similarly. Teamfights determine outcome.",
        "win_condition": "Use ult to engage and win teamfights.",
        "counter_items": ["Mercury's Treads", "Banshee's Veil"],
        "scaling": "Even — both scale at similar rates",
        "jungle_gankable": true,
        "positioning": "Keep distance. Use ult for teamfights."
      },
      "Orianna": {
        "difficulty": "medium",
        "who_wins_early": "Even",
        "trading_pattern": "Orianna has poke. Trade when ball far.",
        "ability_to_dodge": "Orianna Q — dodge by stepping back.",
        "power_spikes": {
          "you": "Level 6 (ult), Luden's",
          "enemy": "Archangel's, Level 6"
        },
        "early_game": "Mirror her playstyle. Both have poke.",
        "mid_game": "Use ult to engage teamfights. Both scale.",
        "late_game": "Both scale similarly. Teamfights determine outcome.",
        "win_condition": "Use ult to engage and win teamfights.",
        "counter_items": ["Mercury's Treads", "Banshee's Veil"],
        "scaling": "Even — both are strong late-game mages",
        "jungle_gankable": true,
        "positioning": "Keep distance. Use ult for engagement."
      },
      "Syndra": {
        "difficulty": "medium",
        "who_wins_early": "Syndra",
        "trading_pattern": "Syndra has poke and burst. Trade when Q down.",
        "ability_to_dodge": "Syndra E — dodge by moving away.",
        "power_spikes": {
          "you": "Level 6 (ult), Luden's",
          "enemy": "Luden's, Level 6"
        },
        "early_game": "Play defensively. Syndra has burst.",
        "mid_game": "Use ult to engage teamfights. Both scale.",
        "late_game": "Both scale similarly. Teamfights determine outcome.",
        "win_condition": "Use ult to engage and win teamfights.",
        "counter_items": ["Mercury's Treads", "Banshee's Veil"],
        "scaling": "Even — both are strong late-game mages",
        "jungle_gankable": true,
        "positioning": "Keep distance. Use ult for teamfights."
      },
      "Lux": {
        "difficulty": "medium",
        "who_wins_early": "Lux",
        "trading_pattern": "Lux has range and poke. Trade when E down.",
        "ability_to_dodge": "Lux E — dodge back.",
        "power_spikes": {
          "you": "Level 6 (ult), Luden's",
          "enemy": "Luden's, Level 6"
        },
        "early_game": "Play defensively. Lux has range.",
        "mid_game": "Use ult to engage teamfights. Both scale.",
        "late_game": "Both scale similarly. Teamfights determine outcome.",
        "win_condition": "Use ult to engage and win teamfights.",
        "counter_items": ["Mercury's Treads", "Banshee's Veil"],
        "scaling": "Even — both are strong late-game mages",
        "jungle_gankable": true,
        "positioning": "Keep distance. Use ult for teamfights."
      },
      "Malzahar": {
        "difficulty": "medium",
        "who_wins_early": "Malzahar",
        "trading_pattern": "Malzahar has sustain and suppress. Trade when E down.",
        "ability_to_dodge": "Malzahar E — respect passive.",
        "power_spikes": {
          "you": "Level 6 (ult), Luden's",
          "enemy": "Liandry's, Level 6"
        },
        "early_game": "Play defensively. Malzahar has sustain.",
        "mid_game": "Use ult to engage. Avoid his suppress.",
        "late_game": "Both scale similarly. Teamfights determine outcome.",
        "win_condition": "Use ult to engage and win teamfights.",
        "counter_items": ["Mercury's Treads", "Spirit Visage"],
        "scaling": "Even — both are strong late-game mages",
        "jungle_gankable": false,
        "positioning": "Keep distance. Use ult for teamfights."
      },
      "Ryze": {
        "difficulty": "medium",
        "who_wins_early": "Even",
        "trading_pattern": "Ryze has mobility and kiting. Trade when Q down.",
        "ability_to_dodge": "Ryze Q — dodge sideways.",
        "power_spikes": {
          "you": "Level 6 (ult), Luden's",
          "enemy": "Luden's, Level 6"
        },
        "early_game": "Mirror his playstyle. Both scale.",
        "mid_game": "Use ult to engage teamfights. Both roam.",
        "late_game": "Both scale similarly. Teamfights determine outcome.",
        "win_condition": "Use ult to engage and win teamfights.",
        "counter_items": ["Mercury's Treads", "Banshee's Veil"],
        "scaling": "Even — both scale at similar rates",
        "jungle_gankable": true,
        "positioning": "Keep distance. Use ult for engagement."
      },
      "Cassiopeia": {
        "difficulty": "medium",
        "who_wins_early": "Cassiopeia",
        "trading_pattern": "Cassio has sustained poke. Trade when W down.",
        "ability_to_dodge": "Cassiopeia W — walk around it.",
        "power_spikes": {
          "you": "Level 6 (ult), Luden's",
          "enemy": "Liandry's, Level 6"
        },
        "early_game": "Play defensively. Cassio has poke.",
        "mid_game": "Use ult to engage teamfights. Both scale.",
        "late_game": "Both scale similarly. Teamfights determine outcome.",
        "win_condition": "Use ult to engage and win teamfights.",
        "counter_items": ["Mercury's Treads", "Banshee's Veil"],
        "scaling": "Even — both are strong late-game mages",
        "jungle_gankable": true,
        "positioning": "Keep distance. Use ult for teamfights."
      },
      "Anivia": {
        "difficulty": "medium",
        "who_wins_early": "Anivia",
        "trading_pattern": "Anivia has range and CC. Trade when Q down.",
        "ability_to_dodge": "Anivia Q — dodge by moving sideways.",
        "power_spikes": {
          "you": "Level 6 (ult), Luden's",
          "enemy": "Archangel's, Level 6"
        },
        "early_game": "Play defensively. Anivia has range.",
        "mid_game": "Use ult to engage teamfights. Both scale.",
        "late_game": "Both scale similarly. Teamfights determine outcome.",
        "win_condition": "Use ult to engage and win teamfights.",
        "counter_items": ["Mercury's Treads", "Banshee's Veil"],
        "scaling": "Even — both are strong late-game mages",
        "jungle_gankable": true,
        "positioning": "Keep distance. Use ult for teamfights."
      },
      "Seraphine": {
        "difficulty": "medium",
        "who_wins_early": "Even",
        "trading_pattern": "Seraphine has poke and utility. Trade when Q down.",
        "ability_to_dodge": "Seraphine E — dodge away.",
        "power_spikes": {
          "you": "Level 6 (ult), Luden's",
          "enemy": "Luden's, Level 6"
        },
        "early_game": "Mirror her playstyle. Both have poke.",
        "mid_game": "Use ult to engage teamfights. Both scale.",
        "late_game": "Both scale similarly. Teamfights determine outcome.",
        "win_condition": "Use ult to engage and win teamfights.",
        "counter_items": ["Mercury's Treads", "Banshee's Veil"],
        "scaling": "Even — both are strong late-game mages",
        "jungle_gankable": true,
        "positioning": "Keep distance. Use ult for teamfights."
      },
      "Viktor": {
        "difficulty": "medium",
        "who_wins_early": "Even",
        "trading_pattern": "Viktor has poke with E. Trade when cooldown down.",
        "ability_to_dodge": "Viktor E — dodge perpendicular.",
        "power_spikes": {
          "you": "Level 6 (ult), Luden's",
          "enemy": "Hexcore upgrade, Liandry's"
        },
        "early_game": "Mirror his playstyle. Both scale.",
        "mid_game": "Use ult to engage teamfights. Both scale.",
        "late_game": "Both scale similarly. Teamfights determine outcome.",
        "win_condition": "Use ult to engage and win teamfights.",
        "counter_items": ["Mercury's Treads", "Banshee's Veil"],
        "scaling": "Even — both are strong late-game mages",
        "jungle_gankable": true,
        "positioning": "Keep distance. Use ult for engagement."
      }
    }
  }
}
