{
  "Yone": {
    "top": {
      "Darius": {
        "difficulty": "medium",
        "who_wins_early": "Darius",
        "trading_pattern": "Darius Q applies bleed. Your E dash and Q range help. Trade EQ from range.",
        "ability_to_dodge": "His Q outer ring bleed — use E dash to create distance and avoid.",
        "power_spikes": {
          "you": "Level 3 (E dash), Trinity Force",
          "enemy": "Level 6 (R execute), Stridebreaker"
        },
        "early_game": "Darius dominates early. Use E to create distance. Trade EQ from range.",
        "mid_game": "Your crit scales. His ult is deadly — maintain distance with E.",
        "late_game": "You outscale through crit and E mobility. He struggles if you space.",
        "win_condition": "Use E to create distance. Trade EQ from range. Scale into crit.",
        "counter_items": ["Trinity Force", "Plated Steelcaps"],
        "scaling": "You outscale through crit and mobility.",
        "jungle_gankable": false,
        "positioning": "Use E to kite. Trade from range. Space carefully."
      },
      "Garen": {
        "difficulty": "medium",
        "who_wins_early": "Garen",
        "trading_pattern": "Garen Q silence dominates close. Your E dash and range help. Trade EQ from distance.",
        "ability_to_dodge": "His Q silence — use E to create distance before he closes.",
        "power_spikes": {
          "you": "Level 3 (E dash), Trinity Force",
          "enemy": "Level 6 (R execute), Sunfire Aegis"
        },
        "early_game": "Garen dominates close. Use E to create distance. Trade EQ.",
        "mid_game": "Your crit scales. His tankiness improves. Maintain distance with E.",
        "late_game": "You outscale through crit. Both scale well.",
        "win_condition": "Use E to create distance. Trade EQ. Scale into crit.",
        "counter_items": ["Trinity Force", "Plated Steelcaps"],
        "scaling": "You outscale through crit and mobility.",
        "jungle_gankable": false,
        "positioning": "Use E to kite. Trade from range. Never close."
      },
      "Fiora": {
        "difficulty": "hard",
        "who_wins_early": "Fiora",
        "trading_pattern": "Fiora's parry negates your damage. Your E dash helps kite. Use E defensively.",
        "ability_to_dodge": "Her parry W — use E to create distance before she parries.",
        "power_spikes": {
          "you": "Level 3 (E dash), Trinity Force",
          "enemy": "Level 3 (parry), Trinity Force"
        },
        "early_game": "Fiora dominates. Use E defensively. Trade from range.",
        "mid_game": "Your crit scales. Her split push is strong. Avoid dueling.",
        "late_game": "You outscale through crit. Fiora struggles if you space.",
        "win_condition": "Use E defensively. Trade from range. Scale into crit.",
        "counter_items": ["Trinity Force", "Hollow Radiance"],
        "scaling": "You outscale through crit and mobility.",
        "jungle_gankable": true,
        "positioning": "Use E defensively. Trade from range. Never duel."
      },
      "Jax": {
        "difficulty": "hard",
        "who_wins_early": "Jax",
        "trading_pattern": "Jax's dueling is oppressive. Your E dash and range help. Trade EQ from distance.",
        "ability_to_dodge": "His E stun — use E to create distance before he engages.",
        "power_spikes": {
          "you": "Level 3 (E dash), Trinity Force",
          "enemy": "Level 6 (E stun), Trinity Force"
        },
        "early_game": "Jax dominates. Use E to create distance. Trade EQ from range.",
        "mid_game": "Your crit scales. His dueling is strong. Avoid close fights.",
        "late_game": "You outscale through crit. Jax struggles if you space.",
        "win_condition": "Use E to create distance. Trade EQ. Scale into crit.",
        "counter_items": ["Trinity Force", "Hollow Radiance"],
        "scaling": "You outscale through crit and mobility.",
        "jungle_gankable": true,
        "positioning": "Use E defensively. Trade from range. Avoid extended."
      },
      "Riven": {
        "difficulty": "skill_matchup",
        "who_wins_early": "even",
        "trading_pattern": "Riven's combo vs your E dash is a skill matchup. Trade EQ around her Q.",
        "ability_to_dodge": "Her Q dash — use E to create distance or trade back.",
        "power_spikes": {
          "you": "Level 3 (E dash), Trinity Force",
          "enemy": "Level 1 (combo), Trinity Force"
        },
        "early_game": "Trade EQ when her Q is down. Use E to space. Respect damage.",
        "mid_game": "Both scale similarly. Use E to trade around her cooldowns.",
        "late_game": "You outscale through crit. Both mobile.",
        "win_condition": "Use E to trade. Space around her combo. Scale into crit.",
        "counter_items": ["Trinity Force", "Plated Steelcaps"],
        "scaling": "You slightly outscale through crit.",
        "jungle_gankable": true,
        "positioning": "Use E to space. Trade EQ. Respect combo."
      },
      "Aatrox": {
        "difficulty": "medium",
        "who_wins_early": "Aatrox",
        "trading_pattern": "Aatrox Q range is massive. Your E dash and Q help. Trade EQ from range.",
        "ability_to_dodge": "His Q skillshots — use E to move away. Trade from distance.",
        "power_spikes": {
          "you": "Level 3 (E dash), Trinity Force",
          "enemy": "Level 1 (Q damage), Goliath Cleaver"
        },
        "early_game": "Aatrox Q dominates. Use E to create distance. Trade from range.",
        "mid_game": "Your crit scales. His all-in is strong. Avoid extended fights.",
        "late_game": "You outscale through crit. He falls off.",
        "win_condition": "Use E to create distance. Trade EQ. Scale into crit.",
        "counter_items": ["Trinity Force", "Plated Steelcaps"],
        "scaling": "You outscale through crit.",
        "jungle_gankable": true,
        "positioning": "Use E to space. Trade from range. Avoid extended."
      },
      "Mordekaiser": {
        "difficulty": "hard",
        "who_wins_early": "Mordekaiser",
        "trading_pattern": "Mordekaiser's all-in is oppressive. Your E dash helps escape. Use E to avoid.",
        "ability_to_dodge": "His E pull — use E to move away before he pulls.",
        "power_spikes": {
          "you": "Level 3 (E dash), Trinity Force",
          "enemy": "Level 1 (all-in), Trinity Force"
        },
        "early_game": "Mordekaiser dominates. Use E defensively. Trade from distance.",
        "mid_game": "Your crit scales. His ult can isolate. Avoid 1v1s.",
        "late_game": "You outscale through crit. He struggles grouped.",
        "win_condition": "Use E defensively. Trade from range. Group for fights.",
        "counter_items": ["Trinity Force", "Hollow Radiance"],
        "scaling": "You outscale through crit.",
        "jungle_gankable": true,
        "positioning": "Use E defensively. Trade from range. Group for fights."
      },
      "Nasus": {
        "difficulty": "easy",
        "who_wins_early": "Yone",
        "trading_pattern": "Nasus has zero early game. Your EQ combos dominate. Trade aggressively.",
        "ability_to_dodge": "His W wither — use E to create distance. Your aggression is stronger.",
        "power_spikes": {
          "you": "Level 1-6 (early dominance), Trinity Force",
          "enemy": "Level 16+ (stacking), Iceborn Gauntlet"
        },
        "early_game": "Dominate with EQ combos. Nasus is helpless. Build a massive lead.",
        "mid_game": "Your lead carries. His stacking helps. Use E to kite.",
        "late_game": "His stacks scale. You outscale through crit. Maintain distance.",
        "win_condition": "Dominate early with EQ. Build lead. Kite late.",
        "counter_items": ["Trinity Force", "Hollow Radiance"],
        "scaling": "He outscales through stacks — you through crit.",
        "jungle_gankable": true,
        "positioning": "Trade aggressively early. Use E to kite late."
      },
      "Sion": {
        "difficulty": "medium",
        "who_wins_early": "even",
        "trading_pattern": "Sion's Q poke is strong. Your E dash helps. Trade EQ carefully.",
        "ability_to_dodge": "His Q slow — use E to create distance and dodge.",
        "power_spikes": {
          "you": "Level 3 (E dash), Trinity Force",
          "enemy": "Level 9 (Q cooldown), Hollow Radiance"
        },
        "early_game": "Trade EQ around his Q cooldowns.",
        "mid_game": "Both scale. Your E helps trading. Trade around cooldowns.",
        "late_game": "Even — both scale well.",
        "win_condition": "Use E to space. Trade EQ. Scale into crit.",
        "counter_items": ["Trinity Force", "Plated Steelcaps"],
        "scaling": "Even — both scale well.",
        "jungle_gankable": true,
        "positioning": "Use E to space. Trade EQ. Respect tankiness."
      },
      "Malphite": {
        "difficulty": "medium",
        "who_wins_early": "Malphite",
        "trading_pattern": "Malphite is tanky but low damage. Your EQ combos help. Trade carefully.",
        "ability_to_dodge": "His E shockwave — use E to create distance.",
        "power_spikes": {
          "you": "Level 3 (E dash), Trinity Force",
          "enemy": "Level 6 (R engage), Thornmail"
        },
        "early_game": "Malphite is hard to kill. Trade EQ. Use E to space.",
        "mid_game": "Your crit scales. His tankiness improves. Avoid extended.",
        "late_game": "Even — both scale well.",
        "win_condition": "Trade EQ carefully. Use E to space. Scale into crit.",
        "counter_items": ["Trinity Force", "Hollow Radiance"],
        "scaling": "Even — both scale well.",
        "jungle_gankable": true,
        "positioning": "Use E to space. Trade EQ. Respect tankiness."
      },
      "Kayle": {
        "difficulty": "medium",
        "who_wins_early": "even",
        "trading_pattern": "Kayle's early range is limited. Your EQ combos are strong. Trade aggressively.",
        "ability_to_dodge": "Her R invincibility — don't commit when she ults.",
        "power_spikes": {
          "you": "Level 1-6 (early dominance), Trinity Force",
          "enemy": "Level 11 (range extends), Nashor's Tooth"
        },
        "early_game": "Dominate with EQ combos. Kayle's range is limited.",
        "mid_game": "Her range extends. Your crit scales. Trade carefully.",
        "late_game": "She scales well. You outscale through crit.",
        "win_condition": "Dominate early with EQ. Build lead. Scale into crit.",
        "counter_items": ["Trinity Force", "Hollow Radiance"],
        "scaling": "Even — both scale well late game.",
        "jungle_gankable": true,
        "positioning": "Trade EQ aggressively early. Scale into crit."
      },
      "Yorick": {
        "difficulty": "medium",
        "who_wins_early": "Yorick",
        "trading_pattern": "Yorick's ghouls are oppressive. Your E dash and range help. Trade from distance.",
        "ability_to_dodge": "His E cage — use E to create distance or move sideways.",
        "power_spikes": {
          "you": "Level 3 (E dash), Trinity Force",
          "enemy": "Level 6 (R maiden), Trinity Force"
        },
        "early_game": "Yorick's ghouls zone you. Use E to trade from range.",
        "mid_game": "Your crit scales. His maiden is strong. Avoid dueling.",
        "late_game": "You outscale through crit. Avoid 1v1s.",
        "win_condition": "Use E to trade from range. Avoid cage. Scale into crit.",
        "counter_items": ["Trinity Force", "Hollow Radiance"],
        "scaling": "You outscale through crit.",
        "jungle_gankable": true,
        "positioning": "Use E to trade from range. Avoid maiden."
      },
      "Illaoi": {
        "difficulty": "medium",
        "who_wins_early": "Illaoi",
        "trading_pattern": "Illaoi's E test is devastating. Your E dash helps kite. Trade from distance.",
        "ability_to_dodge": "Her E tentacle test — use E to move away from her.",
        "power_spikes": {
          "you": "Level 3 (E dash), Trinity Force",
          "enemy": "Level 6 (R spawns), Sunfire Aegis"
        },
        "early_game": "Illaoi's tentacles zone you. Use E to trade from range. Avoid E.",
        "mid_game": "Your crit scales. Her tentacles zone. Trade carefully.",
        "late_game": "You outscale through crit. Avoid tentacles.",
        "win_condition": "Use E to trade from range. Avoid E test. Scale into crit.",
        "counter_items": ["Trinity Force", "Hollow Radiance"],
        "scaling": "You outscale through crit.",
        "jungle_gankable": true,
        "positioning": "Use E to kite. Space from tentacles. Trade EQ."
      },
      "Camille": {
        "difficulty": "hard",
        "who_wins_early": "Camille",
        "trading_pattern": "Camille's E hook is oppressive. Your E dash helps escape. Use E defensively.",
        "ability_to_dodge": "Her E hook — use E to create distance before she hooks.",
        "power_spikes": {
          "you": "Level 3 (E dash), Trinity Force",
          "enemy": "Level 3 (E hook), Trinity Force"
        },
        "early_game": "Camille dominates. Use E defensively. Trade from range.",
        "mid_game": "Your crit scales. Her dueling is strong. Avoid close fights.",
        "late_game": "You outscale through crit. Avoid dueling.",
        "win_condition": "Use E defensively. Trade from range. Scale into crit.",
        "counter_items": ["Trinity Force", "Hollow Radiance"],
        "scaling": "You outscale through crit.",
        "jungle_gankable": true,
        "positioning": "Use E defensively. Trade from range. Avoid E."
      },
      "Olaf": {
        "difficulty": "medium",
        "who_wins_early": "Olaf",
        "trading_pattern": "Olaf's Q slow is oppressive. Your E dash and range help. Trade EQ from distance.",
        "ability_to_dodge": "His Q axe slow — use E to create distance.",
        "power_spikes": {
          "you": "Level 3 (E dash), Trinity Force",
          "enemy": "Level 1 (Q slow), Trinity Force"
        },
        "early_game": "Olaf's poke dominates. Use E to space. Trade from range.",
        "mid_game": "Your crit scales. His R makes him unkiteable. Use E wisely.",
        "late_game": "You outscale through crit. Avoid his ult.",
        "win_condition": "Use E to space. Trade from range. Scale into crit.",
        "counter_items": ["Trinity Force", "Hollow Radiance"],
        "scaling": "You outscale through crit.",
        "jungle_gankable": true,
        "positioning": "Use E to kite. Trade from range. Avoid Q slow."
      },
      "Ornn": {
        "difficulty": "hard",
        "who_wins_early": "Ornn",
        "trading_pattern": "Ornn's W brittle is oppressive. Your E dash helps escape. Use E defensively.",
        "ability_to_dodge": "His E charge — use E to create distance before he charges.",
        "power_spikes": {
          "you": "Level 3 (E dash), Trinity Force",
          "enemy": "Level 6 (R knockup), Sunfire Aegis"
        },
        "early_game": "Ornn dominates. Use E defensively. Trade from range.",
        "mid_game": "Your crit scales. His tankiness improves. Avoid extended.",
        "late_game": "You outscale through crit. His upgrades are annoying.",
        "win_condition": "Use E defensively. Trade from range. Scale into crit.",
        "counter_items": ["Trinity Force", "Hollow Radiance"],
        "scaling": "You outscale through crit.",
        "jungle_gankable": true,
        "positioning": "Use E defensively. Trade from range. Avoid E."
      },
      "Maokai": {
        "difficulty": "medium",
        "who_wins_early": "Maokai",
        "trading_pattern": "Maokai's W pull is strong. Your E dash helps escape. Use E defensively.",
        "ability_to_dodge": "His W pull — use E to create distance before he pulls.",
        "power_spikes": {
          "you": "Level 3 (E dash), Trinity Force",
          "enemy": "Level 6 (R CC chain), Liandry's"
        },
        "early_game": "Maokai's poke is strong. Use E to space. Trade from range.",
        "mid_game": "Your crit scales. His tankiness improves. Avoid extended.",
        "late_game": "Even — both scale well.",
        "win_condition": "Use E to space. Trade from range. Scale into crit.",
        "counter_items": ["Trinity Force", "Hollow Radiance"],
        "scaling": "Even — both scale well.",
        "jungle_gankable": true,
        "positioning": "Use E to space. Trade from range. Respect W."
      },
      "Gnar": {
        "difficulty": "medium",
        "who_wins_early": "Gnar",
        "trading_pattern": "Gnar's poke from range is oppressive. Your E dash helps. Trade around his cooldowns.",
        "ability_to_dodge": "His E hop — use E to create distance from him.",
        "power_spikes": {
          "you": "Level 3 (E dash), Trinity Force",
          "enemy": "Level 1 (ranged poke), Trinity Force"
        },
        "early_game": "Gnar's ranged poke dominates. Use E to space. Trade carefully.",
        "mid_game": "Your crit scales. His mega form is scary. Avoid him.",
        "late_game": "You outscale through crit. Avoid his mega.",
        "win_condition": "Use E to space. Trade around cooldowns. Scale into crit.",
        "counter_items": ["Trinity Force", "Hollow Radiance"],
        "scaling": "You outscale through crit.",
        "jungle_gankable": true,
        "positioning": "Use E to space. Trade around cooldowns. Avoid mega."
      },
      "Volibear": {
        "difficulty": "hard",
        "who_wins_early": "Volibear",
        "trading_pattern": "Volibear's W bite is oppressive. Your E dash helps escape. Use E defensively.",
        "ability_to_dodge": "His R storm dive — use E to move away from impact zone.",
        "power_spikes": {
          "you": "Level 3 (E dash), Trinity Force",
          "enemy": "Level 6 (R engage), Trinity Force"
        },
        "early_game": "Volibear dominates. Use E defensively. Trade from range.",
        "mid_game": "Your crit scales. His tankiness improves. Avoid extended.",
        "late_game": "You outscale through crit. Avoid his all-in.",
        "win_condition": "Use E defensively. Trade from range. Scale into crit.",
        "counter_items": ["Trinity Force", "Plated Steelcaps"],
        "scaling": "You outscale through crit.",
        "jungle_gankable": false,
        "positioning": "Use E defensively. Trade from range. Avoid W."
      }
    }
  }
}